{
  "coordinador-almacen-centralizado-analisis-de-inventario-y-gestion-de-almacen": {
    "id": "coordinador-almacen-centralizado-analisis-de-inventario-y-gestion-de-almacen",
    "cargo": "Coordinador Almacen Centralizado (Analisis de Inventario y Gestion de Almacen)",
    "gerencia": "operaciones",
    "nombre": "Kora",
    "cedula": "",
    "fechaIngreso": "",
    "telefono": "",
    "email": "",
    "estadoCivil": "",
    "nivelAcademico": "",
    "tieneHijos": "",
    "cantidadHijos": "",
    "notas": "",
    "perfilRol": {
      "descripcion": "",
      "gamificacion": {
        "xp": 50,
        "nivel": 1,
        "cursosComp": 1,
        "logros": []
      }
    }
  }
}